{"use_chars": true, "Kb": 0, "Kt": 480, "K4": 0, "C": 10000, "bigrams": [], "trigrams": ["off", "m a", "anc", "mak", "ume", "pla", "guy", "fic", "hee", "hon", "ked", "t f", "ork", "ies", " mu", "rdi", " gu", "ty_", " yo", "bei", " no", "whe", " ju", "hro", "poo", "eak", "ous", "ve ", " or", "m i", "ark", "ink", "ogr", "ic ", "blo", "dis", "col", "app", "low", "clo", "ili", "ot ", "epi", "ano", "rso", "aki", " fl", "ldr", "cor", "ont", "cin", "ppy", "ery", "dir", "up ", "ngi", "ody", "bod", "oun", "sts", "rk ", "ade", "how", "lor", "rke", "ven", "chi", "aro", "des", "eep", "ryi", "tha", "loo", "was", "t h", "se_", "oto", "den", "ns_", "g u", "ond", " di", "cha", "pre", "ive", "hat", "am ", "ves", "mpi", "in_", "o s", "cam", "ge ", "act", "pho", "run", "bus", "ls ", " la", "cro", "kat", "arr", "rls", "rd ", "riv", "ped", "avi", " li", "nex", "pos", "ttl", "ans", "eth", " sa", "ska", " sm", "ren", "oss", "ung", "shi", "th_", "hol", "to ", "omp", "stu", "wim", "tor", "aph", "son", "lac", "g l", "ani", "ty ", "ari", "vin", "fou", " le", "tod", "no ", "ess", "icy", "bic", "ted", "cle", "rie", "hei", "ir ", "pro", "hey", "ami", "r__", "ew ", "irt", "ded", "ows", "the", "ace", "ang", "odd", "op ", "lee", "e n", "ce_", "e k", "d c", "eri", "t w", "ow ", "doo", "lks", "tog", "ar_", "bla", "gam", "r d", "oar", "age", "ad ", "pic", "lea", "ilk", "t s", "erf", " cr", "com", "h a", "owi", "er_", "ppi", "fri", "ear", "ett", "rki", "ect", "nni", "rde", "fig", "bri", "nta", "m__", "ivi", "nto", "sto", " ra", "he ", "air", "oth", "ddl", "rit", " ki", "ble", "tra", " ga", "as ", "oge", "lit", "tic", "teb", "isc", " sk", "rom", "ase", "rme", "cho", "itt", "sti", "rms", "s d", "hap", "abl", "roo", "k o", "fro", "bow", "hai", "ban", " go", "h h", "igh", " fr", "ean", "ppe", "bea", "a r", " pa", "ope", "ck ", " it", "lay", "aye", "uck", "acr", "opp", "sle", " ne", "y o", "de ", "now", "nsi", " pl", " of", "thi", " sc", " vi", "oug", "ben", "cat", "has", "tan", "a y", "ugh", "ssi", "ed_", "d m", "ine", "gra", "ros", "n m", "ood", "row", "ong", "coo", "hin", "ay ", "an_", "y h", "rop", "nds", "oom", "pai", " ea", "min", "k a", "rse", "tea", "unn", " ri", "ld ", "gro", "wor", "mot", " po", "nea", "nge", "tru", " lo", "ost", "uma", "g r", "se ", "jum", "enc", "ws ", "tti", "sel", "scu", " tw", "arm", "ms ", "y c", "fac", "oot", "hed", "d o", " en", "f t", "tow", "g w", " gi", " fa", "ron", " ve", "che", "ily", "por", "o a", "it ", "r o", "ays", "itc", "cer", "ump", "oat", "alk", "put", "dan", "ll ", "ffi", "get", "lad", "og_", "meo", "nts", "eet", "ch_", "ast", "t b", "et_", "ict", "ndo", "tdo", "utd", "gh ", "bou", "iti", "ait", "mpe", "e j", "g s", "ext", "n b", "on_", "ail", "rds", "njo", " dr", "ks ", "arg", "l i", "ide", "ee ", "ild", "g g", " bi", "a h", "ien", "r f", "hom", "idi", "owl", " ac", "rs_", "ke ", "hit", " ma", "ake", "ys ", " tr", " ad", "hav", "eat", "by ", "ed ", "ach", "o g", "hum", "joy", "y s", "ch ", "g c", "ove", "nki", "led", "eni", " by", "yer", "k i", "r s", "way", "ad_", "she", "nd ", "hil", "ore", "et ", "war", "rid", "n h", "ut ", "t a", "wea", "a g", "tar", "s f", "ook", "or ", "s t", "lli", "g n", "oin", "mmi", "imm", "eti", "nk ", "e l", "ctu", "wn_", "man", " ci", "win", "ket", "n w", "let", " an", "sed", "mou", "its", "l__", "p o", "tre", "ns ", "ike", "g j", "dy ", "st ", "l w", "n c", "ant", "rea", "ats", " do", "ard", "boa", "ile", "me ", "tsi", "es ", "ric", " ta", " al"], "fourgrams": [], "char_coef": [[1.432896157031771, -1.6828680571156298, -0.5251714998005672, -2.5693432949125024, 0.5489395889957145, -0.48605546319097287, -0.6454521325119149, -1.1981811135289753, 1.2281457645751686, 2.589749084052054, 0.34881150404123684, 0.46309073311310056, 0.16453501369855925, -2.094813479315637, 0.06689389201823034, -0.22651772243147816, -4.080008177840946, -0.5189729893087102, 0.5955169194403731, -0.23985910625043824, -1.540527937087888, 1.022708814118338, 0.750843101365099, -0.1896528648902842, -0.19880635679050318, -11.261173678867301, -0.9956331793775608, 0.19390716488754833], [-0.13311854477399676, 0.40595580954738747, 1.024872848969598, 0.797450784550759, -0.04162526827365298, 0.46750759326495345, -0.060133535421465524, 2.3497060931681317, 0.5266193549632681, -2.0420012690460467, -2.302379004561748, -1.0806167146900878, 0.27230858915511574, 0.40051588744808725, 1.0028925958966493, -0.08167194907447821, 8.975820277553849, 1.7626556500367445, -0.21869335709495766, 0.4903573065204719, 1.4632357332666681, -0.9934049755229486, -1.1487877363257697, -1.069629453386117, 1.2952166203921744, 4.753524726564319, -0.25983927775836535, 0.052256340783439284], [-1.2997776122453517, 1.2769122475968202, -0.49970134916461517, 1.7718925103202603, -0.5073143207181704, 0.018547869926645748, 0.7055856679393967, -1.151524979619903, -1.7547651195425553, -0.5477478150010352, 1.9535675005620177, 0.6175259815802834, -0.43684360284323676, 1.6942975918513261, -1.0697864879217405, 0.308189671504769, -4.895812099702783, -1.243682660738809, -0.37682356234489456, -0.25049820027172637, 0.07729220384614614, -0.02930383859105555, 0.3979446349421951, 1.2592823182998216, -1.0964102635873372, 6.507648952236994, 1.2554724571405078, -0.24616350567037065]], "bigram_coef": [], "trigram_coef": [[-11.050362542770161, 9.89053796331599, 13.150373650503036, 15.077860311090694, 23.972706388730757, -8.726866208863525, 1.2064694615260148, 0.6769156335820816, 22.101637259021796, 24.065004918713946, 15.251748954627194, 21.02995027377705, 26.306610937696043, 11.384170649486391, 20.709100861341692, 8.583201166632653, 6.740391384416865, -12.714764446526742, 11.267811611833562, 14.57145599674717, -8.335035090498748, -4.227632756442821, 6.093659373236583, 6.732439177108179, 15.015496554401853, 14.174691343953874, -21.903682974635014, 3.3560010600360126, 15.892088105462603, 10.443727073955625, -12.349547149243278, 18.30050132222638, 20.833539782872883, -17.96020920067752, 14.618069483457278, -1.3037758542635576, -18.621043818669943, -6.658402876099575, -8.036679626676353, 2.0448288597674527, 2.383724995800918, 9.501043877689671, -15.289159394379991, 0.10735967916332005, 13.697356247719188, -4.969676834849559, -14.419069290550905, -2.30335603318937, 8.121569954994975, 7.556715819156642, -6.3377250789623965, 14.55766044947126, -21.544756126630865, -2.3684163237275926, 4.551666383372746, 10.19792294775551, 9.85083228540933, 9.85083228540933, 11.24686412490024, -24.49922417613761, 1.1636391525744472, -24.89290861529442, 9.911087708600974, 14.428163766890936, -13.298009279545125, 9.959728663900838, -8.944019505630958, 1.9527826720308208, 10.199164932301997, -2.586449124521892, -14.292310107051547, 11.638747369650526, 6.317785944986523, -14.005571829733398, 3.3708918306009936, 7.621267593556511, 13.712890618837669, 9.703138123793233, -4.0016381779014445, -3.5516236631634377, -7.13027205058314, 3.890969533648056, -2.3155815207475556, 12.853647445990564, -4.659566312256058, -4.234639468641517, 5.295276141267616, 9.021876312645244, 11.148687352713996, -7.9569233313965135, 6.285759198361737, 8.089423903376819, 11.63590928038485, 0.293025810732942, -21.61562912015932, -3.2192362213552874, -11.09936336980071, -9.941371807002238, -7.18433728082244, -11.546327383742684, -1.752689713053645, 13.245836283040063, 9.41600854620773, 8.763011167930339, 6.971982110632529, 4.198970312201901, -0.5738658909696768, -11.349949539857915, 14.332589960650386, 14.643817096488812, 20.2947715743338, 4.666195301927043, 8.118083679506492, -8.687596256625532, -7.600918564878661, 0.6543991184619704, 6.705491443111915, 2.4621790798476533, -7.91540900378865, -7.520483033968269, -1.5624189571770701, 3.8821310872899706, 5.998137169030309, 5.692782197285397, -9.42517476124388, -5.5920646436248775, -9.574452700155943, 16.88007772102975, -10.40165013494992, -0.29585749966953817, -3.8123751301055395, -3.9563075512651538, -1.650357025886301, -8.941860569791816, 7.138036378637591, 5.114222572229691, -11.028885687413304, -12.911276766499132, -11.32187345321996, -0.9903217668945132, 12.625707215842617, 12.625707215842617, 2.3874858456240897, -3.302873325043684, -17.382352930766935, -12.920322528678286, 5.340615424695306, -9.249387692689332, -12.495308745913865, 10.304084198552653, 11.657468751090608, -6.699198573667315, 9.343306580081348, -2.319747907260997, 6.867889451572011, 6.12014907644447, 4.856599579551693, -4.68839438571266, 9.555976003913242, 5.208264300174271, -6.704746618616611, -7.41571749016262, -2.9201861689760236, -8.708811887221605, -8.679838407201322, -4.119239954803046, -5.882781143163566, 5.468065854415861, -4.372880388215138, 0.8359676816146342, -23.813118488746632, -11.989007785467898, -1.3610052171229259, -10.110612450270397, -3.5485318547492635, -10.21071774965376, -2.6548664945135467, 5.66444849328087, -2.1811893910842315, -2.8254563758894937, -0.2443628013059232, -7.989274219653618, 12.33026554379359, 9.5854099033002, 13.580304085303425, 4.70190640489574, -4.402240887544251, -10.22123042988349, 1.4514004343326297, 8.349701839467157, 9.833974272245973, 1.8873508856175158, -8.007590062474174, -3.411996960623871, 2.8583290764452807, -1.3399260940326787, 0.4716088374936793, 7.975402664451367, -1.1855008590154477, -5.614502664242822, -5.592673045976823, 3.7993308000354578, 1.0021005881121487, -8.720554146859438, -6.668676751583945, 0.7722098535611613, -2.720400922246198, 5.422388625880054, -5.446969292277734, 6.1553996989494575, 12.551285696040187, 0.8169164148628528, 9.18836802574266, 11.739285886021957, 15.268249988655649, -2.4416233186088783, 1.6322770379496105, 18.604817182504284, -7.309366559467315, 1.6867221372982246, -18.499308812412487, 1.6799408985259083, -10.732927829739273, 4.090559414864042, -5.957381843103185, 5.445055634597956, -16.13905880027497, 4.251838237321815, 3.6241997041999943, -6.778914994363302, 4.852372768455624, 3.588791424279433, 9.009211845207322, 3.6678892966802743, -9.0006909213246, 7.60485886728535, -7.944091286617509, -10.695711010467438, -0.32688643416649077, -8.36280207379788, -1.7037910018064606, 0.09725625687743732, -5.714879263916248, 8.354436558497119, 3.686467924905594, -1.028579895312341, 3.0017163275828196, 5.146005046757929, 3.7092466545676026, -1.364978779481134, -5.222213172243427, 8.013051562965435, -15.035872527629254, 5.599871092845344, 0.5313876309251119, 4.108958554522933, -0.0906844838893603, 3.583059658046634, -8.384245203923312, 4.415492676367911, 2.2087253750528193, -11.161723974842014, -5.485823007641375, -1.2084348863312415, 14.516058284887947, 13.244107613744584, -7.985608801666758, -9.450939476963418, 4.699347131583543, -10.56560723002696, -3.6953922868130773, -1.9997811836520916, -4.258679807549601, 3.1009052521842766, -8.950797706668947, 0.2232223006312727, 1.814711652012705, -7.771717297179749, 2.3913127092191355, 4.630393772509586, 2.5908667748934398, 2.6534112018265614, 12.98537035203211, -4.261563975129262, -5.017072000158001, -10.927628444783235, 6.04732217054686, 7.3679460682691875, -2.6842340081444127, -3.1740587430321896, 0.7776365141862968, -11.878888359498562, 5.054455526123348, 4.199926183534716, -10.010729199022194, 9.166295363055633, -1.339480791056228, 0.8300953280254472, -2.5761347609756085, -18.39824811710639, 4.159684803081713, -8.205233357750439, -1.8607606638211924, -11.525334099895266, -4.464147792082924, -3.6262536010813826, -2.353590510109548, 7.234225100060981, 3.683466227688561, -0.39901441492546247, -3.7352907746841946, -3.61567163772095, -13.788736052678836, 5.876054627941229, -5.059343380128555, 6.684334377471107, 7.835831521866746, 13.881509577868268, 5.629812653944798, -5.762809914883259, 7.918671690353737, -0.9916300455536299, -11.88457724092546, 5.821951986344015, 7.4425009326002165, 5.128889652297092, -0.9288092749791135, 4.46896679932734, -5.476387683903564, -10.036866813543128, 5.3199507287982675, 8.952408700261852, 5.414189076171229, -5.7027141969633535, 2.7210926715622623, -8.416384872226494, -5.143204558561886, -2.6841763959476213, -1.691328979951725, 5.6004073879362055, -0.11364600412139153, -5.02275524140024, 7.435280554377562, -1.8319813985416205, -1.9239022735717035, -4.662427055421239, -6.057548027758097, 2.4970501091815276, -2.5212992672855186, 16.137922309794263, 3.200329570810446, 5.070641494847036, -4.188080502876641, 6.8798766587535445, 5.928331707834521, -13.038008745185547, -7.158153592884426, -0.8219441528667716, -3.1085443718819046, 10.250371537678165, 10.576445222510278, 10.576445222510278, -9.529855393427129, 0.9163243472198875, -4.418919971225613, 6.785467296907212, -15.834622892796556, -6.601182808715772, 6.354974475303589, 3.2310306202603196, -0.8326995643828088, 4.499991373860524, -0.8785019045143453, -11.282493000816398, -10.584960806579913, -3.7732366457293978, -4.188356753368442, -3.6236837669467064, 3.5318206283752835, 4.429297048348505, -0.15940154813163784, 13.005203414043205, 0.129947279760764, -4.223870586811999, -5.186453907264468, -0.9837871125310106, -0.22090732908303434, -2.6381563247990165, 5.546845462275892, -0.26637067182639185, 8.602326285805685, -5.776207402361228, 2.0643057537598954, -3.3199234312189745, -1.7624159881868298, -4.181669750093154, 1.733218699904023, 4.7852612627004305, 7.995247668029852, -5.797329933010413, -4.791555662935883, 6.722129537389692, -0.5211232880118326, 2.5023454633745765, 2.098052952404075, 4.296580318365132, 0.33419752646808704, -3.1713610665694687, -2.3091445012724736, 1.390186493146253, -6.412729248450255, -8.857060044458244, -0.48334192107385493, 5.774843305331907, 3.746691450691929, 5.499536645256595, 3.1833871481020624, 3.450982337612981, -3.7445267805901103, 4.527312793642343, 1.9192785851372303, 0.4355274724377584, -0.42038625087930975, 1.8542686915285724, -0.7804017987998778, 2.888162056742917, -7.718319785260482, 5.22699898912937, -4.1365109771451145, 3.171257952484612, 0.4669003034230218, 2.6899520358755895, -1.617060107306211, 7.054722401763456, -2.8107971194873413, -8.489383300096218, -1.9676056835588565, -3.9457379542650797, -4.953716064180487, -5.851381855414165, 4.774025995008225, 4.774025995008225, -0.8485795260789185, -10.074975150539878, 4.165578557429451, 10.952725459286965, 2.293269240147826, 0.2805268216607958, 5.960189014698202, -0.6626089154176364, -0.6034240050716483, 3.2453884672990583, -6.097659881966151, 4.1270755758955895, 2.561790184853035, -5.4227275244010205, -3.847332911344895, -1.1214557025084537, -0.9671819641370014, -3.4593953786661698, 0.9058881852061101, 9.484981021364018, -3.0169113033175625, -9.358968576475124, -1.5081452690487325, 5.459366313919532, -3.1842991987162104, -1.7701446133424648, -3.815447356170951, 1.7362856269482365, 3.5453093705087295, 1.3649887038905926, 4.753423711422941, 1.4995175304642956, -0.31435389869296204, 0.8035234558320441, -4.438576114808789, 0.9508866998921502, 0.9126916380109646, 1.4873590765486437], [-17.43357801993912, 7.675223300085727, 0.40129186903926023, -10.695674404420966, -7.073780804182205, 17.809869817811112, -22.44470172299383, 22.57879424264381, -17.820883886916135, 10.24332287929702, -23.373517038269412, -10.294403465906585, -12.408187531303655, 7.006140729310407, -11.51131015262651, 6.123853760647222, 12.764049462868293, 3.235258292745015, 0.9656775207097121, -10.208805578182243, -2.5895850974483845, 4.69883361477597, 5.751293500241701, -14.53170100277304, -7.0687082356078745, 4.443187863008098, 8.449445963154158, -11.414646362144587, -5.245872924061648, 2.1960365662173107, 5.993739297075144, -16.021713297598303, -29.815345353296195, 6.689530058989822, -15.840506257853223, 25.205247282049033, 20.100870014923622, 9.112878460808398, 11.398711300727943, -11.948471897375242, -11.936840864515736, -1.9447649433713419, 6.586419996337412, -8.500617412838732, -19.980117187960094, 10.440513237838074, 2.047019976344819, 9.446416568671584, -1.1393560014857644, -4.956420988938959, 4.114033009393468, 4.461601536154946, 9.75375837388163, 13.60347943474344, 5.098852574531797, 4.818028546384873, -11.763426175660863, -11.763426175660863, -6.537535428962022, 17.67977586425378, -8.745296095337816, 16.08973760086622, -5.724679683519179, -12.38874799981538, 2.687714860739073, -0.48973571375366093, -6.740847184076956, -18.821413442550693, -13.413623448327547, -12.220734166311791, 3.159683867467629, -15.609033809707393, 2.990379815815199, -0.8144917569650817, -8.628240734166576, -2.283694470954048, 14.578142714723336, -5.2044780574015785, -5.516193292950253, -4.517097960449449, 13.541325558258704, -11.580664115258092, 13.272386760684887, -1.3820779829339869, 12.233550165767086, 11.89362365417249, -13.088455803866342, -8.875325569604522, 2.8671936016385873, -0.2753011859527862, 9.82731356274454, -9.986726916146804, -1.6966181472673583, -6.971547121108615, -11.607023165044325, -5.3216576376028195, 4.756883123623613, 0.7161147008414425, 6.862037127738165, 5.986308645129728, -8.554147836707099, -1.7532016976438722, 0.9313996182758213, 2.092563427447359, -11.393900777850709, 19.130254535865642, -14.145709183168472, 5.432912685637634, -13.914473131282579, -2.3595751530566194, -28.595204657847376, 7.491140082392361, -16.557864565060783, 6.3363532734661305, 10.12342123746406, 7.03464130770413, -10.733951148004465, 6.376254241804589, 1.6710629904384995, -6.186228102163462, -5.862235023423515, 1.9282593053643817, 1.6284891680438456, -20.14944808477423, 7.555250933185541, -6.908248101158256, -1.103975630950087, -5.876869785813952, 17.224966802056247, -7.396497046916508, -6.255910096492573, 11.174713600753464, -8.024932163885232, 2.0142497847072836, 7.989887033081119, -0.6175252594040836, 5.885884597364109, 0.2896459996546928, -0.9448153359433414, 7.098783115729796, -11.091959522162334, -11.091959522162334, -0.9622453760595594, -9.10640920312957, -0.7507423591827737, -2.8042192295304122, 11.406208668934928, 9.96254799055911, 9.283400116699214, -6.621243596302163, -14.948982500345219, 11.150703338196797, 1.770548214784881, 9.159817962030537, 26.693374415149027, -7.618135675464767, -6.4640424682448785, 0.9073257386618526, 0.2966673097701165, -0.5361619918228302, 9.506244926342376, 12.354289807035055, -0.6610404096180289, 1.598844705347277, 5.211296884877967, -2.643908344372483, -0.7392222123074172, -8.98184777483442, 15.53852801558086, 1.34137196428387, 25.729953149788766, 7.132545483770767, -0.2527932255241446, 5.681037174830755, 7.443883319746515, -14.663175253775577, 5.759924278920135, 0.3244196072102043, -7.0933863612316275, 10.861435129021983, 8.604317911490577, 3.5338051526018326, -6.2440456809166, -8.688321576746574, 5.682938813354459, -1.5361869871262326, 10.242663261193208, 13.813425125323874, -5.9083855724560905, 6.25005032310852, -9.458257931905772, 7.495643792623935, 0.7383202791793961, -3.7084237890237794, 2.2705604966032715, 5.185761081774383, -9.337854500949996, -6.7882865384761715, 4.813810481185249, 0.41496404019177285, -1.7754118537312844, -10.972324679520998, 7.563298270493684, 5.184164014120606, 6.552336230723648, -7.741409578213272, 7.41641898392513, -2.7853395099350666, 2.4987073111896194, -0.27978912750861057, -28.25639636573161, -4.1181229740131595, -5.440146071855414, 3.810015186836143, -3.3520396211685166, 13.394680043961369, 7.7815861764708, -15.651679079773066, -1.5612671175958912, 4.349655248413959, 10.409627073570025, -6.697713175868135, 7.467246251193708, -12.652342799321584, 10.093585729620541, -11.728193046619591, 7.939731725007776, -3.2244061680672447, 3.7583172955864184, 26.709358960325833, -11.475766301844542, 3.1209493275743094, -11.306030865298153, -0.8277322597236191, 5.598499372107155, -2.1718319198123517, 3.403654620035821, 5.144531961623993, 5.319821603935015, 6.01050920551552, -5.648383026383594, -17.366014451420874, 0.9585152708366267, -0.8698580251757173, 3.4166477848668375, 8.075875188243552, 2.533916920142026, 0.8685724473910572, -10.603195059916397, -7.690480070343001, -0.002423393341774146, -7.466121574654914, 1.5465584368405747, -1.5455185935598836, 11.971832550228152, 1.5423792510409766, -3.8510874239420487, 1.2998143347857374, 6.245310982573088, -5.582980775157357, -1.1566381234446783, 7.474707553751914, 9.36974599613019, 4.105130039384006, -17.207133720588732, -9.889289353145221, 1.1963288741528053, -6.17050071264307, 1.0669692162985678, 4.619543827882512, 10.15209944870334, -5.0551217407896445, 3.15226006603967, -4.695589639076407, 4.7479596831716435, 2.5319205260537787, -10.538888399690325, 3.53270873417157, 0.8011856633911879, 0.07725360628502687, -3.916386234817034, -0.21831200605810022, -1.85427208441683, -2.4421692191769573, 7.779710944441174, 7.62825052251801, -6.996697001349206, -3.359362459732687, -3.97729277310477, -2.2948334306074587, -6.448923821751853, 6.025157489602308, 1.6848594511083186, -6.40606158093895, 9.618797908451123, -5.164372542943548, 6.344849006669819, 2.964903412611576, -1.886058809095356, 14.629622945464973, -7.155752794543257, 1.6285597892231671, -12.422319686671322, 2.7966755466613273, -1.5212051689781554, 6.022436343253279, -3.850176739778398, 8.116603530779788, 6.646176359804036, 0.46267333062753935, -3.043134174311714, 5.441541373484044, -16.376709449633143, -10.441201327437462, 4.678945585107398, -8.038504748708046, -0.3046680942528474, -6.502204785932585, -7.430476929050375, 6.251686795574475, -2.9801033336035565, -4.93458887153934, 10.475304808633348, -3.1463368744911584, -10.653628351622109, 3.162548529367303, 5.397031796366115, -3.1461517814734736, 0.7061868244943988, 8.992967482750133, 3.162437873599234, 0.929950647346648, -3.1188331940614114, 0.776399165366494, -1.143510776331815, 0.7267039674296124, -3.9187154751105537, 3.3729889742653403, 4.029552826821311, -5.157855116543223, 0.6152371860369891, -1.1484357687445736, -16.844337221362892, 5.169272658742988, 11.799811280252467, -3.372018674924169, 5.490273608740418, -0.7687566100290247, 2.5046279122481736, -5.98524897163236, -3.999602223436041, -8.80594919702852, 6.998616645594486, -4.279966571569141, -4.145321052078817, 9.27911554418703, 4.945702852345464, 6.302109263266714, 9.763113200283186, -19.395191256469946, -11.98972134479731, -11.98972134479731, 11.764820689957272, 1.5912632021203004, 0.435991717478191, -0.5637421637886383, 11.423920984723031, 6.964912594917093, -1.6402940786440317, 0.15840103714448178, -2.380323737030853, 0.9080814115109959, -1.892548507117696, -0.831450161576593, 11.257552840361905, -3.4868283612035382, -2.5651484624140317, 4.285829517341927, 0.7184754132903548, -5.639243093724295, -3.4553668582908648, -7.0413533126933245, 2.7296189396040424, 5.6770582306048665, 0.9713357889903228, 0.8548335996857126, -3.176196695776504, 3.6522175072870637, -8.58336218017168, 1.2406178635142209, -2.4698118839687146, -0.7190638693922624, 2.144642763265335, 4.705368148036463, 2.036262550400415, 3.862591620686061, -3.8893742691426465, 1.0830652420339433, -9.51678305074685, 8.013564649827655, 4.318007187409292, 4.852344665575135, -2.5654323220288373, 0.804837435341268, -3.6578090671213226, -11.822020047229502, 4.079393610601108, 4.066730937807255, -2.55635820825166, 4.341128056040198, 4.60703444859626, 11.432587337345582, 5.2726590190205656, -0.8749307451594354, -8.823044262268995, -2.694087372204974, -3.9912279376523867, -4.77522472044254, 3.340446707430127, -10.12966234873956, -2.787719011948247, 4.0468129892310545, 7.07430521669414, 2.137350923155344, 5.62733903976886, 1.4025175471460838, 0.9566003757877928, -0.47152293217327085, -2.259285098861272, -1.533686379863886, 6.3007556128617495, -3.107309180584187, -5.383743841062888, -1.5431866144293307, 1.616753372014593, 3.9037112303160155, 3.6645727594285007, 3.3995947150898673, -0.9445423410435709, 4.050351377835634, 2.491471888535408, 2.491471888535408, 4.760012314958386, 11.773525862292923, -2.3376736413602974, -8.673870127558498, -0.41164784760720285, -0.9068659187766874, 0.09624852685489804, 5.925495818112107, -4.761954308414944, -2.518803056075625, 0.35312432191541243, -2.8967281144083517, 0.09947461116521622, 5.442343699948247, -2.1323567039868725, 1.7701878153045723, -0.9713396734422535, -1.3335183025608288, 3.436232293817625, -7.062408079396905, 0.16878564714963745, 0.6735157457279661, -4.753561763870059, 2.2790165770861, -0.30829445099999087, -1.8881911397072275, -1.0835507481072648, -7.468963659745638, -0.6984832386217845, 0.987808495224456, 7.534674995338124, -7.574504534630513, 2.285501258770917, 5.030958223327213, 5.655824607420776, -5.477473824143308, -4.667385620441339, -3.435349630007404], [28.483940562655757, -17.565761263547813, -13.551665519583917, -4.382185906890857, -16.89892558466917, -9.08300360915828, 21.238232261449483, -23.255709876283298, -4.280753372224686, -34.308327797691206, 8.121768083519536, -10.735546807852684, -13.89842340642099, -18.390311378838824, -9.197790708958665, -14.707054927258659, -19.50444084722051, 9.479506153857074, -12.233489132581646, -4.3626504185645345, 10.924620187837268, -0.47120085845373333, -11.844952873340956, 7.799261825648702, -7.946788318924699, -18.61787920661048, 13.454237011554895, 8.058645302011934, -10.646215181556881, -12.639763640260174, 6.355807852086708, -2.278788024576855, 8.981805569778123, 11.270679141780109, 1.2224367743786733, -23.901471427823356, -1.4798261959419794, -2.4544755846955466, -3.362031673967054, 9.90364303765099, 9.553115868804015, -7.556278934206682, 8.702739398286882, 8.393257733711923, 6.282760940172742, -5.470836403008731, 12.372049314031699, -7.143060535369812, -6.982213953463184, -2.600294830117405, 2.2236920696184037, -19.01926198569768, 11.790997752582879, -11.23506311097009, -9.650518957725712, -15.01595149385722, 1.9125938904203743, 1.9125938904203743, -4.709328695984705, 6.8194483118246225, 7.581656942994063, 8.803171014340538, -4.186408025198113, -2.039415766839409, 10.610294418635014, -9.469992950100274, 15.684866689729217, 16.8686307703355, 3.214458516025458, 14.807183290944849, 11.132626239518249, 3.97028644005685, -9.308165760696431, 14.820063586639156, 5.257348903547984, -5.337573122704142, -28.291033333142177, -4.498660066315177, 9.517831470800878, 8.068721623555978, -6.411053507662969, 7.689694581823637, -10.956805239994711, -11.471569463199415, -7.573983853623596, -7.6589841854319145, 7.793179662441493, -0.1465507431032836, -14.015880954344194, 8.232224517422472, -16.113072761059716, 1.897303012816153, -9.939291133052825, 6.67852131042357, 33.222652285221464, 8.540893859027848, 6.342480246132827, 9.225257106319365, 0.3223001531248057, 5.560018738475503, 10.306837549652162, -11.492634585280582, -10.347408164512233, -10.855574595278192, 4.421918667034165, -23.32922484819324, 14.719575074135617, 5.917036854100949, -0.41811682949018547, -12.284241943641742, 8.300433083498929, -12.157335384437173, 8.439780885333423, 2.351242983196282, -2.522502672637636, -7.689040426160294, 4.028459704839685, -8.838433321573136, 6.244346013273999, 13.706711136068694, 7.4246539806481, -5.810390392664346, -7.626626336974725, 14.456665887513754, 1.8699238280026467, 12.500312744986866, 10.678428331291965, -11.003207935080475, -6.823316667119771, 7.6923545467134735, 10.068285226863903, -7.218406049500856, 9.675289189813759, 6.927610785056111, -15.127923411828995, -4.4966973128796885, 5.143001090065973, 12.62163076679762, 12.266688789272678, -6.1084613487743145, -1.5337476937768573, -1.5337476937768573, -1.4252404695980128, 12.409282528251218, 18.13309528981188, 15.724541758220793, -16.746824093722463, -0.7131602977666747, 3.211908629266841, -3.6828406022875813, 3.2915137491091353, -4.451504764545639, -11.113854794624574, -6.840070054705797, -33.56126386630315, 1.4979865990438543, 1.6074428887463716, 3.781068647028187, -9.852643313678715, -4.672102308374138, -2.801498307637635, -4.938572316914517, 3.581226578637154, 7.109967181899302, 3.468541522302524, 6.763148299199568, 6.622003355575429, 3.513781920411385, -11.16564762741286, -2.1773396458476086, -1.9168346613834941, 4.856462301569407, 1.6137984426133816, 4.429575275588472, -3.895351464918986, 24.873893003346854, -3.1050577844122667, -5.988868100481771, 9.274575752285205, -8.035978753164537, -8.359955110019913, 4.455469067023935, -6.086219862870418, -0.8970883263573256, -19.26324289862551, -3.1657194177966894, -5.840422373602296, -3.5921946951480095, 4.4569851381605545, -14.599752162598048, -0.37571634021757333, -9.382994678232613, 7.269269783271659, 7.120420749646037, -5.128889573120989, -3.8458349877189115, 8.866245663516061, -1.1871161260209067, -3.6283096222544686, 5.199538624063898, 7.368084899679328, 7.172993879485106, -8.565398858545795, 3.536390132793116, 0.11634052091459904, 6.969199724624439, -4.696018061668917, -2.637049115956279, 2.9482619809785127, -5.875610571505058, 15.70511066924765, 3.301206559151514, -3.7482219538291157, -15.549301072969955, -11.916210367389962, -10.953056725377582, -9.41386321437984, -2.9531381025977312, 8.870633676972508, -6.03637738573908, 8.089681738708798, 5.017772277408865, 3.2656815783806303, 8.561783384337902, -4.13620388659132, 6.283137411938148, 8.19932707517237, -1.0274320692202432, -7.382516999796843, -19.930443965865855, 6.623393533379912, -6.709740751764344, 2.2968190200469842, -2.84015703697285, 3.4021915493047525, -5.433026947520082, 4.540436666704841, 5.55117904882758, -4.9929351698746665, 2.352292868310353, 7.352174028307039, 17.268758194531546, 4.7563639931461905, -7.484578533240067, -7.103115709739707, -7.047295292934418, -5.535633247871795, -6.014577494212109, 6.8939484052696685, 9.055458849737413, 5.224636565537968, -0.5469299882345198, 13.489314090919212, -4.054352499287074, -12.503220181358945, -5.651337805556201, 3.9417719078589495, -4.882873992803413, 2.138934221442513, 1.1674880988395517, -1.0520872516227593, 3.687016421115413, -3.883922988564057, -2.8966951530569682, 2.6910754357141995, -3.3548182605842762, 6.789279927725044, 15.621440189667414, -5.766316347884883, 5.946063402054954, -6.456707161846836, 7.05490292441391, 1.1064197414950259, 1.5946843868471305, 4.202838023532057, -2.7551428267133273, 8.72417674781368, 4.239008563038263, -3.192498372572369, -4.707647378798678, 1.3255194599110218, -2.4350991957912886, -11.131098267826463, 6.7037331944353005, -2.762638944498016, 3.2993779224344637, 0.9493748307569402, -4.008583608605168, 6.6615267812286065, 5.468892173699992, 5.671287307566256, 5.853730869854931, -6.739314977161049, 2.2061353974398807, 0.3919312906290909, -4.001922820161954, -5.005368215618103, -3.7949987405924666, 4.462193570035367, 3.7686251716210837, 2.9960679914497828, 6.576673568492267, 14.283080350562328, 8.728658553290622, 5.985352960920727, -2.3961827421101036, 6.203767249900478, -15.350828630977684, -10.32964258754098, -0.06365891570715722, 6.778424949024764, -1.8258697357852585, 30.16544550207679, 4.5651466995391905, 0.3803977949507457, 1.3541703712072535, -7.531163427635316, -7.379304792062482, 1.8006642752475701, -0.4888768806602327, -4.938568356809195, 5.926218917224782, 1.4092724322222943, -2.675615111800866, 3.2111274190898462, -8.291438181503304, -4.468222521476517, -1.3228150179003109, 4.770200859381873, 1.0438993308127058, -8.482388602369923, -9.882359347548723, -2.2953558821086792, 4.92631503159245, -1.577581895253612, 7.689680904925579, 9.061920033552706, -0.6888125782569614, -2.3382238468344543, -0.4425522714627825, -0.5015911819077353, 6.171191010001784, 9.409056666893262, -3.3372912602363454, -9.875909006553313, 8.034445730411841, 0.5672744189667918, -1.7282934991765435, 0.01667135507386817, -10.152673338099051, 0.7992726526511534, 3.7353077021680376, -2.8105361426876505, -2.5999100872694387, -1.7830106556892829, 3.758893201018451, 2.2124507405533116, -5.480165110506721, -6.654568828336403, 9.144819718780994, 1.4132761223394954, 1.4132761223394954, -2.234965296488418, -2.50758754935393, 3.9829282537656314, -6.221725133112218, 4.410701908034695, -0.36372978625608793, -4.714680396621175, -3.3894316574214503, 3.2130233014241973, -5.408072785468751, 2.771050411651538, 12.113943162382634, -0.6725920339288838, 7.260065006905439, 6.753505215841434, -0.6621457504834137, -4.250296041667652, 1.2099460452920225, 3.614768406412327, -5.963850101340788, -2.859566219356648, -1.4531876438001239, 4.215118118159328, 0.1289535128389601, 3.397104024847398, -1.0140611824962236, 3.0365167180154478, -0.9742471916964329, -6.132514401947901, 6.495271271743041, -4.208948516999301, -1.3854447168652808, -0.2738465622136917, 0.31907812940005364, 2.1561555692517165, -5.868326504686834, 1.521535382683168, -2.216234716778951, 0.473548475584619, -11.574474202987423, 3.086555610080053, -3.3071828986843874, 1.559756114653126, 7.525439728791043, -4.413591137070419, -0.8953698712039214, 4.865502709516479, -5.731314549167134, 1.8056947998351234, -2.5755272927657593, -4.789317097997909, -4.899912560179219, 5.076352811575345, -2.8054492730556335, 0.8078407894811798, 1.3242423828649932, 0.40408007316349936, 5.602349555040794, 0.8684404268330874, -4.482340461745453, -6.653918965831046, -3.9916196147292533, -4.846937241042711, -4.29067960389865, 6.7617194094432, -4.755476056949777, 6.395796076033175, -1.6375715725807347, -6.767655916283655, 0.4173571447452137, 7.000803948300233, -5.511535787329861, 1.1940437474722618, 4.585672069747031, -1.6969670758940971, 0.5461432392041241, 5.898258405180924, 1.8010304776232262, -7.265497883606726, -7.265497883606726, -3.9114327889154628, -1.6985507117995748, -1.827904916048748, -2.278855331773802, -1.881621392550124, 0.6263390971134035, -6.056437541410221, -5.262886902662254, 5.365378313493479, -0.7265854112161262, 5.744535560103408, -1.2303474614732932, -2.6612647960383677, -0.01961617553470986, 5.9796896153018855, -0.6487321127985649, 1.9385216375775893, 4.792913681148977, -4.342120479058558, -2.4225729420141993, 2.848125656205689, 8.685452830748858, 6.261707032889488, -7.738382891034956, 3.492593649693635, 3.658335753094727, 4.898998104244813, 5.732678032664344, -2.846826131908146, -2.352797199123711, -12.288098706738088, 6.074987004124277, -1.9711473600861231, -5.834481679108344, -1.217248492710825, 4.526587124259719, 3.7546939824721894, 1.9479905533958422]], "fourgram_coef": [], "intercept": [-2.658055575986752, -8.219363730226181, 10.877419306183105]}